{
  "falhas": {
    "daily-generator": {
      "data": "2026-06-20",
      "count": 8,
      "ultimaFalha": "2026-06-20T22:06:03.940Z"
    },
    "story-07h": {
      "data": "2026-06-20",
      "count": 7,
      "ultimaFalha": "2026-06-20T22:06:03.969Z"
    },
    "kling-reel-20h": {
      "data": "2026-06-20",
      "count": 4,
      "ultimaFalha": "2026-06-20T22:06:03.998Z"
    },
    "fiscal-hooks-kling": {
      "data": "2026-06-20",
      "count": 3,
      "ultimaFalha": "2026-06-20T22:06:05.103Z"
    },
    "carousel-12h": {
      "data": "2026-06-20",
      "count": 2,
      "ultimaFalha": "2026-06-20T22:06:04.025Z"
    }
  },
  "ultimaVerificacao": "2026-06-20T22:06:05.547Z",
  "schedule_alerta_2026-06-09": "2026-06-06",
  "schedule_alerta_2026-06-14": "2026-06-11",
  "schedule_alerta_2026-06-19": "2026-06-16",
  "schedule_alerta_2026-06-20": "2026-06-19",
  "schedule_alerta_2026-06-21": "2026-06-20"
}